{
	"normal": {
		"ships": [535, 615, 895, 595, 632, 565, 465, 535, 615, 895, 632, 595, 565, 465, 24, 25, 479, 480, 486, 113, 99, 24, 25, 9, 10, 32, 11, 12, 33, 13, 14, 34, 35, 36, 37, 61, 14, 100, 101, 42, 43, 44, 45, 46, 47, 95, 96, 97, 98, 48, 49, 17, 18, 19, 14],
		"replace": [
			{"id": 21, "slots": [1, 8]},
			{"id": 22, "slots": [2, 9]},
			{"id": 23, "slots": [3, 11]},
			{"id": 53, "slots": [0, 7]},
			{"id": 54, "slots": [5, 12]},
			{"id": 55, "slots": [4, 10]},
			{"id": 56, "slots": [6, 13]}
		]
	}, 
	"boss": {
		"ships": [],
		"replace": [
		]
	}
}